odoo/addons/sale_order_line_field_from_product_attribute/README.md
odoo/addons/sale_order_line_field_from_product_attribute/README.rst
odoo/addons/sale_order_line_field_from_product_attribute/__init__.py
odoo/addons/sale_order_line_field_from_product_attribute/__manifest__.py
odoo/addons/sale_order_line_field_from_product_attribute/i18n/it.po
odoo/addons/sale_order_line_field_from_product_attribute/i18n/sale_order_line_field_from_product_attribute.pot
odoo/addons/sale_order_line_field_from_product_attribute/models/__init__.py
odoo/addons/sale_order_line_field_from_product_attribute/models/product_attribute.py
odoo/addons/sale_order_line_field_from_product_attribute/models/sale_order_line.py
odoo/addons/sale_order_line_field_from_product_attribute/readme/CONFIGURE.rst
odoo/addons/sale_order_line_field_from_product_attribute/readme/CONTRIBUTORS.rst
odoo/addons/sale_order_line_field_from_product_attribute/readme/DESCRIPTION.rst
odoo/addons/sale_order_line_field_from_product_attribute/readme/USAGE.rst
odoo/addons/sale_order_line_field_from_product_attribute/static/description/icon.png
odoo/addons/sale_order_line_field_from_product_attribute/static/description/index.html
odoo/addons/sale_order_line_field_from_product_attribute/tests/__init__.py
odoo/addons/sale_order_line_field_from_product_attribute/tests/test_sale_attribute.py
odoo/addons/sale_order_line_field_from_product_attribute/views/product_attribute_view.xml
odoo_addon_sale_order_line_field_from_product_attribute-16.0.1.0.0.4.dist-info/METADATA
odoo_addon_sale_order_line_field_from_product_attribute-16.0.1.0.0.4.dist-info/WHEEL
odoo_addon_sale_order_line_field_from_product_attribute-16.0.1.0.0.4.dist-info/top_level.txt
odoo_addon_sale_order_line_field_from_product_attribute-16.0.1.0.0.4.dist-info/RECORD
