Metadata-Version: 2.1
Name: odoo-addon-sale-order-line-field-from-product-attribute
Version: 16.0.1.0.0.4
Summary: Store Attribute value sis Sales Order line fields
Home-page: https://github.com/OCA/sale-workflow
Author: Open Source Integrators, Odoo Community Association (OCA)
Author-email: support@odoo-community.org
License: AGPL-3
Platform: UNKNOWN
Classifier: Programming Language :: Python
Classifier: Framework :: Odoo
Classifier: Framework :: Odoo :: 16.0
Classifier: License :: OSI Approved :: GNU Affero General Public License v3
Classifier: Development Status :: 4 - Beta
Requires-Python: >=3.10
Requires-Dist: odoo <16.1dev,>=16.0a
